README.md
setup.cfg
setup.py
psycho_orm_frankenstein.egg-info/PKG-INFO
psycho_orm_frankenstein.egg-info/SOURCES.txt
psycho_orm_frankenstein.egg-info/dependency_links.txt
psycho_orm_frankenstein.egg-info/requires.txt
psycho_orm_frankenstein.egg-info/top_level.txt
py2sql/__init__.py
py2sql/py2sql.py
test/__init__.py