Metadata-Version: 2.1
Name: psycho-orm-frankenstein
Version: 0.0.3
Summary: A toy ORM tool
Home-page: https://github.com/gevorgyana/lab3
Author: Artyom Gevorgyan
Author-email: artemhevorhian@gmail.com
License: UNKNOWN
Platform: UNKNOWN
Classifier: Programming Language :: Python :: 3
Classifier: License :: OSI Approved :: MIT License
Classifier: Operating System :: OS Independent
Requires-Python: >=3.8
